suumo_scraping/__init__.py
suumo_scraping/suumo.py
suumo_scraping-0.0.1.dist-info/METADATA
suumo_scraping-0.0.1.dist-info/WHEEL
suumo_scraping-0.0.1.dist-info/licenses/LICENSE
suumo_scraping-0.0.1.dist-info/RECORD
