Metadata-Version: 2.1
Name: suumo_scraping
Version: 0.0.1
Summary: suumo web scraping package
Project-URL: Homepage, https://github.com/Asano-Naoki/suumo_scraping
Project-URL: Issues, https://github.com/Asano-Naoki/suumo_scraping/issues
Author-email: Asano Naoki <asannaoki@gmail.com>
License-File: LICENSE
Classifier: License :: OSI Approved :: GNU Affero General Public License v3
Classifier: Operating System :: OS Independent
Classifier: Programming Language :: Python :: 3
Requires-Python: >=3.8.10
Requires-Dist: bs4==0.0.1
Requires-Dist: requests>=2.28.2
